dagster_duckdb_pandas/__init__.py
dagster_duckdb_pandas/duckdb_pandas_type_handler.py
dagster_duckdb_pandas/py.typed
dagster_duckdb_pandas/version.py
dagster_duckdb_pandas-0.28.13.dist-info/licenses/LICENSE
dagster_duckdb_pandas-0.28.13.dist-info/METADATA
dagster_duckdb_pandas-0.28.13.dist-info/WHEEL
dagster_duckdb_pandas-0.28.13.dist-info/top_level.txt
dagster_duckdb_pandas-0.28.13.dist-info/RECORD
